glyles/__init__.py
glyles/__main__.py
glyles/converter.py
glyles/glycans/__init__.py
glyles/glycans/factory/__init__.py
glyles/glycans/factory/factory.py
glyles/glycans/factory/factory_f.py
glyles/glycans/factory/factory_o.py
glyles/glycans/factory/factory_p.py
glyles/glycans/mono/__init__.py
glyles/glycans/mono/enum_c.py
glyles/glycans/mono/monomer.py
glyles/glycans/mono/reactor.py
glyles/glycans/mono/reactor_basic.py
glyles/glycans/poly/__init__.py
glyles/glycans/poly/anltr_error_listener.py
glyles/glycans/poly/glycan.py
glyles/glycans/poly/gwb_glycan.py
glyles/glycans/poly/gwb_walker.py
glyles/glycans/poly/merger.py
glyles/glycans/poly/viz.py
glyles/glycans/poly/walker.py
glyles/glycans/poly/wurcs_glycan.py
glyles/glycans/poly/wurcs_walker.py
glyles/glycans/utils.py
glyles/gwb/GWB.g4
glyles/gwb/GWB.interp
glyles/gwb/GWB.tokens
glyles/gwb/GWBLexer.interp
glyles/gwb/GWBLexer.py
glyles/gwb/GWBLexer.tokens
glyles/gwb/GWBListener.py
glyles/gwb/GWBParser.py
glyles/iupac/IUPAC.g4
glyles/iupac/IUPAC.interp
glyles/iupac/IUPAC.tokens
glyles/iupac/IUPACLexer.interp
glyles/iupac/IUPACLexer.py
glyles/iupac/IUPACLexer.tokens
glyles/iupac/IUPACListener.py
glyles/iupac/IUPACParser.py
glyles/version.py
glyles/wurcs/WURCS.g4
glyles/wurcs/WURCS.interp
glyles/wurcs/WURCS.tokens
glyles/wurcs/WURCSLexer.interp
glyles/wurcs/WURCSLexer.py
glyles/wurcs/WURCSLexer.tokens
glyles/wurcs/WURCSListener.py
glyles/wurcs/WURCSParser.py
glyles-1.2.2.dist-info/LICENSE
glyles-1.2.2.dist-info/METADATA
glyles-1.2.2.dist-info/WHEEL
glyles-1.2.2.dist-info/entry_points.txt
glyles-1.2.2.dist-info/RECORD
