Metadata-Version: 2.3
Name: glyles
Version: 1.2.2
Summary: A tool to convert IUPAC representation of glycans into SMILES strings
Author: Roman Joeres
Author-email: roman.joeres@helmholtz-hips.de
Requires-Python: >=3.9,<4.0
Classifier: Development Status :: 5 - Production/Stable
Classifier: License :: OSI Approved :: MIT License
Classifier: Operating System :: OS Independent
Classifier: Programming Language :: Python :: 3
Classifier: Programming Language :: Python :: 3.9
Classifier: Programming Language :: Python :: 3.10
Classifier: Programming Language :: Python :: 3.11
Classifier: Programming Language :: Python :: 3.12
Classifier: Programming Language :: Python :: 3.13
Requires-Dist: antlr4-python3-runtime (==4.13.2)
Requires-Dist: antlr4-tools (>=0.2.1)
Requires-Dist: joblib (>=1.2.0,<2.0.0)
Requires-Dist: networkx (>=2.6.3)
Requires-Dist: numpy
Requires-Dist: pydot (>=1.4.2,<2.0.0)
Requires-Dist: rdkit (>=2021.9.2)
Project-URL: Repository, https://github.com/kalininalab/GlyLES
